ridge_detector/__init__.py
ridge_detector/constants.py
ridge_detector/correct.py
ridge_detector/detector.py
ridge_detector/utils.py
ridge_detector-0.1.2.dist-info/LICENSE
ridge_detector-0.1.2.dist-info/METADATA
ridge_detector-0.1.2.dist-info/WHEEL
ridge_detector-0.1.2.dist-info/top_level.txt
ridge_detector-0.1.2.dist-info/RECORD
