Metadata-Version: 2.1
Name: ridge-detector
Version: 0.1.2
Summary: A multi-scale ridge detector for identifying curvilinear structures in images
Home-page: https://github.com/lxfhfut/ridge-detector.git
Author: Gavin Lin
Author-email: lxfhfut@gmail.com
Classifier: Programming Language :: Python :: 3
Classifier: License :: OSI Approved :: MIT License
Classifier: Operating System :: OS Independent
License-File: LICENSE
